dobble/__init__.py
dobble/config.py
dobble/main.py
dobble/data/emojis.txt
dobble/game/__init__.py
dobble/game/card.py
dobble/game/game.py
dobble/game/player.py
dobble/ui/components.py
dobble/ui/display.py
dobble/ui/input.py
dobble/utils/emoji_loader.py
pydobble-1.0.8.dist-info/METADATA
pydobble-1.0.8.dist-info/WHEEL
pydobble-1.0.8.dist-info/entry_points.txt
pydobble-1.0.8.dist-info/licenses/LICENSE
pydobble-1.0.8.dist-info/RECORD
